COPYING
LICENSE
MANIFEST.in
README.rst
setup.py
django_missing.egg-info/PKG-INFO
django_missing.egg-info/SOURCES.txt
django_missing.egg-info/dependency_links.txt
django_missing.egg-info/not-zip-safe
django_missing.egg-info/requires.txt
django_missing.egg-info/top_level.txt
docs/Makefile
docs/conf.py
docs/debug.rst
docs/index.rst
docs/javascript.rst
docs/middleware.rst
docs/templatetags.rst
docs/timezone.rst
docs/views.rst
docs/_ext/django-dummy.py
missing/__init__.py
missing/admindocs.py
missing/debug.py
missing/middleware.py
missing/models.py
missing/timezone.py
missing/views.py
missing/static/missing/date.js
missing/static/missing/humanize.js
missing/static/missing/n11n.js
missing/static/missing/n11ndata.js
missing/static/missing/urlify.js
missing/static/missing/urlify2.js
missing/templates/missing/heading.html
missing/templatetags/__init__.py
missing/templatetags/context_tags.py
missing/templatetags/forloop_tags.py
missing/templatetags/html_tags.py
missing/templatetags/lang_tags.py
missing/templatetags/list_tags.py
missing/templatetags/string_tags.py
missing/templatetags/url_tags.py
missing/tests/__init__.py
missing/tests/context_urls.py
missing/tests/safereporting_urls.py
missing/tests/test_missing.py
missing/tests/urltemplate_urls.py
missing/utils/__init__.py
missing/utils/buffer.py
missing/utils/decorators.py
missing/utils/locker.py
missing/utils/urllib.py