Metadata-Version: 1.1
Name: django-missing
Version: 1.0.1
Summary: Some missing features in Django. Are not missing anymore.
Home-page: https://github.com/wlanslovenija/django-missing
Author: Mitar
Author-email: development@wlan-si.net
License: AGPLv3
Platform: UNKNOWN
Classifier: Development Status :: 4 - Beta
Classifier: Environment :: Web Environment
Classifier: Intended Audience :: Developers
Classifier: License :: OSI Approved :: GNU Affero General Public License v3
Classifier: Operating System :: OS Independent
Classifier: Programming Language :: Python
Classifier: Framework :: Django
